element_miniscope/__init__.py
element_miniscope/miniscope.py
element_miniscope/miniscope_report.py
element_miniscope/version.py
element_miniscope-0.3.2.dist-info/LICENSE
element_miniscope-0.3.2.dist-info/METADATA
element_miniscope-0.3.2.dist-info/WHEEL
element_miniscope-0.3.2.dist-info/top_level.txt
element_miniscope-0.3.2.dist-info/RECORD
