Metadata-Version: 2.1
Name: element-miniscope
Version: 0.3.2
Summary: Miniscope DataJoint Element
Home-page: https://github.com/datajoint/element-miniscope
Author: DataJoint
Author-email: info@datajoint.com
License: MIT
Keywords: neuroscience calcium-imaging science datajoint miniscope
Platform: UNKNOWN
License-File: LICENSE
Requires-Dist: datajoint (>=0.13.0)
Requires-Dist: element-interface (>=0.3.0)
Requires-Dist: opencv-python
